agent/__init__.py
agent/__main__.py
agent/agent_cli.py
agent/connectors/__init__.py
agent/connectors/base.py
agent/connectors/core.py
agent/connectors/tun.py
agent/utils/__init__.py
agent/utils/bootstrap_agent.py
agent/utils/messages.py
agent/utils/opentun.py
agent/utils/packet_dumper.py
agent/utils/rmq_handler.py
agent/utils/serial_listener.py
agent/utils/pure_pcapy/__init__.py
ioppytest_agent-0.2.20.data/data/FAQ.md
ioppytest_agent-0.2.20.data/data/INSTALL.md
ioppytest_agent-0.2.20.data/data/LICENSE
ioppytest_agent-0.2.20.data/data/README.md
ioppytest_agent-0.2.20.data/data/USAGE.md
ioppytest_agent-0.2.20.data/data/version.py
ioppytest_agent-0.2.20.dist-info/LICENSE
ioppytest_agent-0.2.20.dist-info/METADATA
ioppytest_agent-0.2.20.dist-info/WHEEL
ioppytest_agent-0.2.20.dist-info/entry_points.txt
ioppytest_agent-0.2.20.dist-info/top_level.txt
ioppytest_agent-0.2.20.dist-info/RECORD
