Metadata-Version: 2.1
Name: ioppytest-agent
Version: 0.2.20
Summary: Component for creating VPN client environments
Home-page: https://github.com/fsismondi/ioppytest-agent
Author: Federico Sismondi
Author-email: federicosismondi@gmail.com
Maintainer: Federico Sismondi
Maintainer-email: federicosismondi@gmail.com
License: GPLv3+
Platform: UNKNOWN
Classifier: Development Status :: 3 - Alpha
Classifier: Intended Audience :: Science/Research
Classifier: Intended Audience :: Developers
Classifier: Programming Language :: Python
Classifier: Programming Language :: Python :: 2
Classifier: Programming Language :: Python :: 2.7
Classifier: Topic :: Internet
Classifier: Topic :: Software Development :: Testing
Classifier: Topic :: Scientific/Engineering
Classifier: Operating System :: POSIX
Classifier: Operating System :: Unix
Classifier: Operating System :: MacOS
Requires-Dist: click
Requires-Dist: six
Requires-Dist: kombu
Requires-Dist: pika
Requires-Dist: pyserial
